sphinx_polyversion/__init__.py
sphinx_polyversion/__main__.py
sphinx_polyversion/api.py
sphinx_polyversion/builder.py
sphinx_polyversion/driver.py
sphinx_polyversion/environment.py
sphinx_polyversion/git.py
sphinx_polyversion/json.py
sphinx_polyversion/log.py
sphinx_polyversion/main.py
sphinx_polyversion/pyvenv.py
sphinx_polyversion/setuptools_scm.py
sphinx_polyversion/sphinx.py
sphinx_polyversion/utils.py
sphinx_polyversion/uv.py
sphinx_polyversion/vcs.py
sphinx_polyversion-2.0.0.dist-info/LICENSE
sphinx_polyversion-2.0.0.dist-info/METADATA
sphinx_polyversion-2.0.0.dist-info/WHEEL
sphinx_polyversion-2.0.0.dist-info/entry_points.txt
sphinx_polyversion-2.0.0.dist-info/RECORD
