Metadata-Version: 2.3
Name: sphinx_polyversion
Version: 2.0.0
Summary: Build multiple versions of your sphinx docs and merge them into one website.
License: MIT
Keywords: utils,documentation,sphinx
Author: yfprojects
Author-email: real-yfprojects@users.noreply.github.com
Requires-Python: >=3.8
Classifier: Development Status :: 2 - Pre-Alpha
Classifier: Intended Audience :: Developers
Classifier: License :: OSI Approved :: MIT License
Classifier: Programming Language :: Python :: 3
Classifier: Programming Language :: Python :: 3.8
Classifier: Programming Language :: Python :: 3.9
Classifier: Programming Language :: Python :: 3.10
Classifier: Programming Language :: Python :: 3.11
Classifier: Programming Language :: Python :: 3.12
Classifier: Programming Language :: Python :: 3.13
Classifier: Topic :: Documentation
Classifier: Topic :: Documentation :: Sphinx
Classifier: Topic :: Software Development :: Documentation
Classifier: Topic :: Utilities
Classifier: Typing :: Typed
Provides-Extra: jinja
Provides-Extra: setuptools-scm
Provides-Extra: virtualenv
Requires-Dist: jinja2 (>=3) ; extra == "jinja"
Requires-Dist: packaging (>=25.0) ; extra == "setuptools-scm"
Requires-Dist: setuptools_scm (>=9.2.0) ; extra == "setuptools-scm"
Requires-Dist: virtualenv (>=20) ; extra == "virtualenv"
Project-URL: Documentation, https://real-yfprojects.github.io/sphinx-polyversion/
Project-URL: Repository, https://github.com/real-yfprojects/sphinx-polyversion
